wordslab_llms/__init__.py
wordslab_llms/_modidx.py
wordslab_llms/models.py
wordslab_llms/data/base_models.csv
wordslab_llms-0.0.3.dist-info/LICENSE
wordslab_llms-0.0.3.dist-info/METADATA
wordslab_llms-0.0.3.dist-info/WHEEL
wordslab_llms-0.0.3.dist-info/entry_points.txt
wordslab_llms-0.0.3.dist-info/top_level.txt
wordslab_llms-0.0.3.dist-info/RECORD
