Metadata-Version: 2.1
Name: wordslab-llms
Version: 0.0.3
Summary: Python library for easy and efficient inference and fine tuning of popular open source llms
Home-page: https://github.com/wordslab-org/wordslab-llms-lib
Author: Laurent Prud'hon
Author-email: laurent.prudhon@hotmail.fr
License: Apache Software License 2.0
Keywords: nbdev jupyter notebook python llm huggingface transformers
Platform: UNKNOWN
Classifier: Development Status :: 4 - Beta
Classifier: Intended Audience :: Developers
Classifier: Natural Language :: English
Classifier: Programming Language :: Python :: 3.9
Classifier: Programming Language :: Python :: 3.10
Classifier: License :: OSI Approved :: Apache Software License
Requires-Python: >=3.9
License-File: LICENSE
Provides-Extra: dev
